COMMUNICATION_PROTOCOLS/SPI/spi_state.v
module spi_state (
    input clk, rst,
    input [15:0] data_in,
    output spi_cs, spi_sclk, spi_data,
    output [4:0] counter
);

reg MOSI;
reg [4:0] count;
reg cs, sclk;
reg [2:0] state;

always @(posedge clk) begin
    if (rst) begin
        MOSI <= 1'd0;
        count <= 5'd16;
        cs <= 1'd1;
        sclk <= 1'd0;
        state <= 3'd0;
    end
    else begin
        case (state)
            0: begin // IDLE
                sclk <= 1'd0;
                cs <= 1'd1;
                state <= 1;
            end 

            1: begin // LOAD BIT
                sclk <= 1'd0;
                cs <= 1'd0;
                if (count > 0) begin
                    MOSI <= data_in[count-1];
                    count <= count - 1;
                end
                state <= 2;
            end

            2: begin // CLOCK HIGH
                sclk <= 1'd1;
                if (count > 0)
                    state <= 1;
                else begin
                    count <= 5'd16;
                    state <= 0;
                end
            end

            default: state <= 0;
        endcase
    end
end

assign spi_cs = cs;
assign spi_sclk = sclk;
assign spi_data = MOSI;
assign counter = count;

endmodule

COMMUNICATION_PROTOCOLS/SPI/spi_state_tb.v
`timescale 1ns/1ps

module spi_state_tb;

    reg clk;
    reg rst;
    reg [15:0] data_in;

    wire spi_cs;
    wire spi_sclk;
    wire spi_data;
    wire [4:0] counter;

    // Instantiate DUT
    spi_state uut (
        .clk(clk),
        .rst(rst),
        .data_in(data_in),
        .spi_cs(spi_cs),
        .spi_sclk(spi_sclk),
        .spi_data(spi_data),
        .counter(counter)
    );

    // Clock generation: 10ns period
    always #5 clk = ~clk;

    initial begin
        // Dump waveform
        $dumpfile("spi_state.vcd");
        $dumpvars(0, spi_state_tb);

        // Initialize signals
        clk = 0;
        rst = 1;
        data_in = 16'hA5A5; // test pattern

        // Apply reset
        #20;
        rst = 0;

        // Let it run for a while
        #500;

        // Change input data mid-simulation
        data_in = 16'h3C7E;

        #500;

        // Finish simulation
        $finish;
    end

endmodule

COMMUNICATION_PROTOCOLS/SPI/spi_state.vcd
$date
	Tue Apr 28 11:51:47 2026
$end
$version
	Icarus Verilog
$end
$timescale
	1ps
$end
$scope module spi_state_tb $end
$var wire 1 ! spi_sclk $end
$var wire 1 " spi_data $end
$var wire 1 # spi_cs $end
$var wire 5 $ counter [4:0] $end
$var reg 1 % clk $end
$var reg 16 & data_in [15:0] $end
$var reg 1 ' rst $end
$scope module uut $end
$var wire 1 % clk $end
$var wire 5 ( counter [4:0] $end
$var wire 16 ) data_in [15:0] $end
$var wire 1 ' rst $end
$var wire 1 # spi_cs $end
$var wire 1 " spi_data $end
$var wire 1 ! spi_sclk $end
$var reg 1 * MOSI $end
$var reg 5 + count [4:0] $end
$var reg 1 , cs $end
$var reg 1 - sclk $end
$var reg 3 . state [2:0] $end
$upscope $end
$upscope $end
$enddefinitions $end
$comment Show the parameter values. $end
$dumpall
$end
#0
$dumpvars
bx .
x-
x,
bx +
x*
b1010010110100101 )
bx (
1'
b1010010110100101 &
0%
bx $
x#
x"
x!
$end
#5000
b0 .
0!
0-
1#
1,
b10000 $
b10000 (
b10000 +
0"
0*
1%
#10000
0%
#15000
1%
#20000
0%
0'
#25000
b1 .
1%
#30000
0%
#35000
b10 .
b1111 $
b1111 (
b1111 +
1"
1*
0#
0,
1%
#40000
0%
#45000
b1 .
1!
1-
1%
#50000
0%
#55000
b10 .
b1110 $
b1110 (
b1110 +
0"
0*
0!
0-
1%
#60000
0%
#65000
b1 .
1!
1-
1%
#70000
0%
#75000
b10 .
b1101 $
b1101 (
b1101 +
1"
1*
0!
0-
1%
#80000
0%
#85000
b1 .
1!
1-
1%
#90000
0%
#95000
b10 .
b1100 $
b1100 (
b1100 +
0"
0*
0!
0-
1%
#100000
0%
#105000
b1 .
1!
1-
1%
#110000
0%
#115000
b10 .
b1011 $
b1011 (
b1011 +
0!
0-
1%
#120000
0%
#125000
b1 .
1!
1-
1%
#130000
0%
#135000
b10 .
b1010 $
b1010 (
b1010 +
1"
1*
0!
0-
1%
#140000
0%
#145000
b1 .
1!
1-
1%
#150000
0%
#155000
b10 .
b1001 $
b1001 (
b1001 +
0"
0*
0!
0-
1%
#160000
0%
#165000
b1 .
1!
1-
1%
#170000
0%
#175000
b10 .
b1000 $
b1000 (
b1000 +
1"
1*
0!
0-
1%
#180000
0%
#185000
b1 .
1!
1-
1%
#190000
0%
#195000
b10 .
b111 $
b111 (
b111 +
0!
0-
1%
#200000
0%
#205000
b1 .
1!
1-
1%
#210000
0%
#215000
b10 .
b110 $
b110 (
b110 +
0"
0*
0!
0-
1%
#220000
0%
#225000
b1 .
1!
1-
1%
#230000
0%
#235000
b10 .
b101 $
b101 (
b101 +
1"
1*
0!
0-
1%
#240000
0%
#245000
b1 .
1!
1-
1%
#250000
0%
#255000
b10 .
b100 $
b100 (
b100 +
0"
0*
0!
0-
1%
#260000
0%
#265000
b1 .
1!
1-
1%
#270000
0%
#275000
b10 .
b11 $
b11 (
b11 +
0!
0-
1%
#280000
0%
#285000
b1 .
1!
1-
1%
#290000
0%
#295000
b10 .
b10 $
b10 (
b10 +
1"
1*
0!
0-
1%
#300000
0%
#305000
b1 .
1!
1-
1%
#310000
0%
#315000
b10 .
b1 $
b1 (
b1 +
0"
0*
0!
0-
1%
#320000
0%
#325000
b1 .
1!
1-
1%
#330000
0%
#335000
b10 .
b0 $
b0 (
b0 +
1"
1*
0!
0-
1%
#340000
0%
#345000
b0 .
b10000 $
b10000 (
b10000 +
1!
1-
1%
#350000
0%
#355000
b1 .
1#
1,
0!
0-
1%
#360000
0%
#365000
b10 .
b1111 $
b1111 (
b1111 +
0#
0,
1%
#370000
0%
#375000
b1 .
1!
1-
1%
#380000
0%
#385000
b10 .
b1110 $
b1110 (
b1110 +
0"
0*
0!
0-
1%
#390000
0%
#395000
b1 .
1!
1-
1%
#400000
0%
#405000
b10 .
b1101 $
b1101 (
b1101 +
1"
1*
0!
0-
1%
#410000
0%
#415000
b1 .
1!
1-
1%
#420000
0%
#425000
b10 .
b1100 $
b1100 (
b1100 +
0"
0*
0!
0-
1%
#430000
0%
#435000
b1 .
1!
1-
1%
#440000
0%
#445000
b10 .
b1011 $
b1011 (
b1011 +
0!
0-
1%
#450000
0%
#455000
b1 .
1!
1-
1%
#460000
0%
#465000
b10 .
b1010 $
b1010 (
b1010 +
1"
1*
0!
0-
1%
#470000
0%
#475000
b1 .
1!
1-
1%
#480000
0%
#485000
b10 .
b1001 $
b1001 (
b1001 +
0"
0*
0!
0-
1%
#490000
0%
#495000
b1 .
1!
1-
1%
#500000
0%
#505000
b10 .
b1000 $
b1000 (
b1000 +
1"
1*
0!
0-
1%
#510000
0%
#515000
b1 .
1!
1-
1%
#520000
0%
b11110001111110 &
b11110001111110 )
#525000
b10 .
b111 $
b111 (
b111 +
0"
0*
0!
0-
1%
#530000
0%
#535000
b1 .
1!
1-
1%
#540000
0%
#545000
b10 .
b110 $
b110 (
b110 +
1"
1*
0!
0-
1%
#550000
0%
#555000
b1 .
1!
1-
1%
#560000
0%
#565000
b10 .
b101 $
b101 (
b101 +
0!
0-
1%
#570000
0%
#575000
b1 .
1!
1-
1%
#580000
0%
#585000
b10 .
b100 $
b100 (
b100 +
0!
0-
1%
#590000
0%
#595000
b1 .
1!
1-
1%
#600000
0%
#605000
b10 .
b11 $
b11 (
b11 +
0!
0-
1%
#610000
0%
#615000
b1 .
1!
1-
1%
#620000
0%
#625000
b10 .
b10 $
b10 (
b10 +
0!
0-
1%
#630000
0%
#635000
b1 .
1!
1-
1%
#640000
0%
#645000
b10 .
b1 $
b1 (
b1 +
0!
0-
1%
#650000
0%
#655000
b1 .
1!
1-
1%
#660000
0%
#665000
b10 .
b0 $
b0 (
b0 +
0"
0*
0!
0-
1%
#670000
0%
#675000
b0 .
b10000 $
b10000 (
b10000 +
1!
1-
1%
#680000
0%
#685000
b1 .
1#
1,
0!
0-
1%
#690000
0%
#695000
b10 .
b1111 $
b1111 (
b1111 +
0#
0,
1%
#700000
0%
#705000
b1 .
1!
1-
1%
#710000
0%
#715000
b10 .
b1110 $
b1110 (
b1110 +
0!
0-
1%
#720000
0%
#725000
b1 .
1!
1-
1%
#730000
0%
#735000
b10 .
b1101 $
b1101 (
b1101 +
1"
1*
0!
0-
1%
#740000
0%
#745000
b1 .
1!
1-
1%
#750000
0%
#755000
b10 .
b1100 $
b1100 (
b1100 +
0!
0-
1%
#760000
0%
#765000
b1 .
1!
1-
1%
#770000
0%
#775000
b10 .
b1011 $
b1011 (
b1011 +
0!
0-
1%
#780000
0%
#785000
b1 .
1!
1-
1%
#790000
0%
#795000
b10 .
b1010 $
b1010 (
b1010 +
0!
0-
1%
#800000
0%
#805000
b1 .
1!
1-
1%
#810000
0%
#815000
b10 .
b1001 $
b1001 (
b1001 +
0"
0*
0!
0-
1%
#820000
0%
#825000
b1 .
1!
1-
1%
#830000
0%
#835000
b10 .
b1000 $
b1000 (
b1000 +
0!
0-
1%
#840000
0%
#845000
b1 .
1!
1-
1%
#850000
0%
#855000
b10 .
b111 $
b111 (
b111 +
0!
0-
1%
#860000
0%
#865000
b1 .
1!
1-
1%
#870000
0%
#875000
b10 .
b110 $
b110 (
b110 +
1"
1*
0!
0-
1%
#880000
0%
#885000
b1 .
1!
1-
1%
#890000
0%
#895000
b10 .
b101 $
b101 (
b101 +
0!
0-
1%
#900000
0%
#905000
b1 .
1!
1-
1%
#910000
0%
#915000
b10 .
b100 $
b100 (
b100 +
0!
0-
1%
#920000
0%
#925000
b1 .
1!
1-
1%
#930000
0%
#935000
b10 .
b11 $
b11 (
b11 +
0!
0-
1%
#940000
0%
#945000
b1 .
1!
1-
1%
#950000
0%
#955000
b10 .
b10 $
b10 (
b10 +
0!
0-
1%
#960000
0%
#965000
b1 .
1!
1-
1%
#970000
0%
#975000
b10 .
b1 $
b1 (
b1 +
0!
0-
1%
#980000
0%
#985000
b1 .
1!
1-
1%
#990000
0%
#995000
b10 .
b0 $
b0 (
b0 +
0"
0*
0!
0-
1%
#1000000
0%
#1005000
b0 .
b10000 $
b10000 (
b10000 +
1!
1-
1%
#1010000
0%
#1015000
b1 .
1#
1,
0!
0-
1%
