COMMUNICATION_PROTOCOLS/SPI/spi_state.v
module spi_state (
    input       clk, rst,
    input       start,                // rising edge triggers a new transmission
    input [15:0] data_in,
    output      spi_cs, spi_sclk, spi_data,
    output      busy,                 // high during transmission
    output      done,                 // single‑cycle pulse at the end
    output [4:0] counter
);

    // SPI mode 0: idle low, data valid on rising edge
    reg        mosi, cs, sclk;
    reg [15:0] shift_reg;             // latched data, shifted left each bit
    reg [4:0]  bits_remaining;        // bits left to send (16,15,...,0)
    reg [1:0]  state;

    // Handshake
    reg        busy_reg;
    reg        done_reg;
    reg        start_d;               // edge detector for 'start'
    wire       start_rise = start && !start_d;

    // States
    localparam IDLE      = 2'b00,
               LOAD_BIT  = 2'b01,
               CLOCK_HIGH= 2'b10;

    always @(posedge clk or posedge rst) begin
        if (rst) begin
            mosi           <= 1'b0;
            cs             <= 1'b1;
            sclk           <= 1'b0;
            shift_reg      <= 16'd0;
            bits_remaining <= 5'd16;
            state          <= IDLE;
            busy_reg       <= 1'b0;
            done_reg       <= 1'b0;
            start_d        <= 1'b0;
        end 
        else begin
            start_d <= start;                     // sample start for edge detection
            done_reg <= 1'b0;                    // default: done pulse low

            case (state)
                IDLE: begin
                    cs       <= 1'b1;
                    sclk     <= 1'b0;
                    busy_reg <= 1'b0;

                    if (start_rise) begin
                        // latch data and begin transmission
                        shift_reg      <= data_in;
                        bits_remaining <= 5'd16;
                        cs             <= 1'b0;  // assert chip select
                        busy_reg       <= 1'b1;
                        state          <= LOAD_BIT;
                    end
                end

                LOAD_BIT: begin
                    sclk <= 1'b0;
                    cs   <= 1'b0;
                    // output MSB first
                    mosi <= shift_reg[15];
                    state <= CLOCK_HIGH;
                end

                CLOCK_HIGH: begin
                    sclk <= 1'b1;                 // rising edge – slave captures
                    // prepare for next bit
                    shift_reg <= {shift_reg[14:0], 1'b0};
                    bits_remaining <= bits_remaining - 1'b1;

                    if (bits_remaining == 5'd1) begin
                        // last bit just sent
                        cs       <= 1'b1;
                        sclk     <= 1'b0;
                        busy_reg <= 1'b0;
                        done_reg <= 1'b1;
                        state    <= IDLE;
                    end else begin
                        state    <= LOAD_BIT;
                    end
                end

                default: state <= IDLE;
            endcase
        end
    end

    // Output assignments
    assign spi_cs   = cs;
    assign spi_sclk = sclk;
    assign spi_data = mosi;
    assign busy     = busy_reg;
    assign done     = done_reg;
    assign counter  = bits_remaining;

endmodule

COMMUNICATION_PROTOCOLS/SPI/spi_state_tb.v
`timescale 1ns/1ps

module spi_state_tb;

    // Inputs
    reg clk;
    reg rst;
    reg start;
    reg [15:0] data_in;

    // Outputs
    wire spi_cs;
    wire spi_sclk;
    wire spi_data;
    wire busy;
    wire done;
    wire [4:0] counter;

    // Instantiate DUT
    spi_state uut (
        .clk(clk),
        .rst(rst),
        .start(start),
        .data_in(data_in),
        .spi_cs(spi_cs),
        .spi_sclk(spi_sclk),
        .spi_data(spi_data),
        .busy(busy),
        .done(done),
        .counter(counter)
    );

    // Clock generation (10ns period → 100MHz)
    always #5 clk = ~clk;

    initial begin
        // Initialize
        clk = 0;
        rst = 1;
        start = 0;
        data_in = 16'h0000;

        // Dump waveform
        $dumpfile("spi_state.vcd");
        $dumpvars(0, spi_state_tb);

        // Reset
        #20;
        rst = 0;

        // Wait a bit
        #20;

        // Send first data
        data_in = 16'hA5A5;
        start = 1;
        #10;
        start = 0;

        // Wait until done
        wait(done);

        #20;

        // Send another data
        data_in = 16'h3C7E;
        start = 1;
        #10;
        start = 0;

        wait(done);

        #50;

        $finish;
    end

    // Monitor signals
    initial begin
        $monitor("Time=%0t | CS=%b SCLK=%b MOSI=%b | BUSY=%b DONE=%b COUNT=%d DATA=%h",
                  $time, spi_cs, spi_sclk, spi_data, busy, done, counter, data_in);
    end

endmodule

COMMUNICATION_PROTOCOLS/SPI/spi_state.vcd
$date
	Thu Apr 30 18:48:59 2026
$end
$version
	Icarus Verilog
$end
$timescale
	1ps
$end
$scope module spi_state_tb $end
$var wire 1 ! spi_sclk $end
$var wire 1 " spi_data $end
$var wire 1 # spi_cs $end
$var wire 1 $ done $end
$var wire 5 % counter [4:0] $end
$var wire 1 & busy $end
$var reg 1 ' clk $end
$var reg 16 ( data_in [15:0] $end
$var reg 1 ) rst $end
$var reg 1 * start $end
$scope module uut $end
$var wire 1 & busy $end
$var wire 1 ' clk $end
$var wire 5 + counter [4:0] $end
$var wire 16 , data_in [15:0] $end
$var wire 1 $ done $end
$var wire 1 ) rst $end
$var wire 1 # spi_cs $end
$var wire 1 " spi_data $end
$var wire 1 ! spi_sclk $end
$var wire 1 * start $end
$var wire 1 - start_rise $end
$var parameter 2 . CLOCK_HIGH $end
$var parameter 2 / IDLE $end
$var parameter 2 0 LOAD_BIT $end
$var reg 5 1 bits_remaining [4:0] $end
$var reg 1 2 busy_reg $end
$var reg 1 3 cs $end
$var reg 1 4 done_reg $end
$var reg 1 5 mosi $end
$var reg 1 6 sclk $end
$var reg 16 7 shift_reg [15:0] $end
$var reg 1 8 start_d $end
$var reg 2 9 state [1:0] $end
$upscope $end
$upscope $end
$enddefinitions $end
$comment Show the parameter values. $end
$dumpall
b1 0
b0 /
b10 .
$end
#0
$dumpvars
b0 9
08
b0 7
06
05
04
13
02
b10000 1
0-
b0 ,
b10000 +
0*
1)
b0 (
0'
0&
b10000 %
0$
1#
0"
0!
$end
#5000
1'
#10000
0'
#15000
1'
#20000
0'
0)
#25000
1'
#30000
0'
#35000
1'
#40000
1-
0'
1*
b1010010110100101 (
b1010010110100101 ,
#45000
0-
b1 9
1&
12
0#
03
b1010010110100101 7
18
1'
#50000
0'
0*
#55000
b10 9
1"
15
08
1'
#60000
0'
#65000
b1 9
b1111 %
b1111 +
b1111 1
b100101101001010 7
1!
16
1'
#70000
0'
#75000
b10 9
0"
05
0!
06
1'
#80000
0'
#85000
b1 9
b1110 %
b1110 +
b1110 1
b1001011010010100 7
1!
16
1'
#90000
0'
#95000
b10 9
1"
15
0!
06
1'
#100000
0'
#105000
b1 9
b1101 %
b1101 +
b1101 1
b10110100101000 7
1!
16
1'
#110000
0'
#115000
b10 9
0"
05
0!
06
1'
#120000
0'
#125000
b1 9
b1100 %
b1100 +
b1100 1
b101101001010000 7
1!
16
1'
#130000
0'
#135000
b10 9
0!
06
1'
#140000
0'
#145000
b1 9
b1011 %
b1011 +
b1011 1
b1011010010100000 7
1!
16
1'
#150000
0'
#155000
b10 9
1"
15
0!
06
1'
#160000
0'
#165000
b1 9
b1010 %
b1010 +
b1010 1
b110100101000000 7
1!
16
1'
#170000
0'
#175000
b10 9
0"
05
0!
06
1'
#180000
0'
#185000
b1 9
b1001 %
b1001 +
b1001 1
b1101001010000000 7
1!
16
1'
#190000
0'
#195000
b10 9
1"
15
0!
06
1'
#200000
0'
#205000
b1 9
b1000 %
b1000 +
b1000 1
b1010010100000000 7
1!
16
1'
#210000
0'
#215000
b10 9
0!
06
1'
#220000
0'
#225000
b1 9
b111 %
b111 +
b111 1
b100101000000000 7
1!
16
1'
#230000
0'
#235000
b10 9
0"
05
0!
06
1'
#240000
0'
#245000
b1 9
b110 %
b110 +
b110 1
b1001010000000000 7
1!
16
1'
#250000
0'
#255000
b10 9
1"
15
0!
06
1'
#260000
0'
#265000
b1 9
b101 %
b101 +
b101 1
b10100000000000 7
1!
16
1'
#270000
0'
#275000
b10 9
0"
05
0!
06
1'
#280000
0'
#285000
b1 9
b100 %
b100 +
b100 1
b101000000000000 7
1!
16
1'
#290000
0'
#295000
b10 9
0!
06
1'
#300000
0'
#305000
b1 9
b11 %
b11 +
b11 1
b1010000000000000 7
1!
16
1'
#310000
0'
#315000
b10 9
1"
15
0!
06
1'
#320000
0'
#325000
b1 9
b10 %
b10 +
b10 1
b100000000000000 7
1!
16
1'
#330000
0'
#335000
b10 9
0"
05
0!
06
1'
#340000
0'
#345000
b1 9
b1 %
b1 +
b1 1
b1000000000000000 7
1!
16
1'
#350000
0'
#355000
b10 9
1"
15
0!
06
1'
#360000
0'
#365000
b0 9
1$
14
0&
02
1#
13
b0 %
b0 +
b0 1
b0 7
0!
06
1'
#370000
0'
#375000
0$
04
1'
#380000
0'
#385000
b1 9
1&
12
0#
03
b10000 %
b10000 +
b10000 1
b11110001111110 7
18
0-
1'
1*
b11110001111110 (
b11110001111110 ,
#390000
0'
#395000
b10 9
0"
05
08
1'
0*
#400000
0'
#405000
b1 9
b1111 %
b1111 +
b1111 1
b111100011111100 7
1!
16
1'
#410000
0'
#415000
b10 9
0!
06
1'
#420000
0'
#425000
b1 9
b1110 %
b1110 +
b1110 1
b1111000111111000 7
1!
16
1'
#430000
0'
#435000
b10 9
1"
15
0!
06
1'
#440000
0'
#445000
b1 9
b1101 %
b1101 +
b1101 1
b1110001111110000 7
1!
16
1'
#450000
0'
#455000
b10 9
0!
06
1'
#460000
0'
#465000
b1 9
b1100 %
b1100 +
b1100 1
b1100011111100000 7
1!
16
1'
#470000
0'
#475000
b10 9
0!
06
1'
#480000
0'
#485000
b1 9
b1011 %
b1011 +
b1011 1
b1000111111000000 7
1!
16
1'
#490000
0'
#495000
b10 9
0!
06
1'
#500000
0'
#505000
b1 9
b1010 %
b1010 +
b1010 1
b1111110000000 7
1!
16
1'
#510000
0'
#515000
b10 9
0"
05
0!
06
1'
#520000
0'
#525000
b1 9
b1001 %
b1001 +
b1001 1
b11111100000000 7
1!
16
1'
#530000
0'
#535000
b10 9
0!
06
1'
#540000
0'
#545000
b1 9
b1000 %
b1000 +
b1000 1
b111111000000000 7
1!
16
1'
#550000
0'
#555000
b10 9
0!
06
1'
#560000
0'
#565000
b1 9
b111 %
b111 +
b111 1
b1111110000000000 7
1!
16
1'
#570000
0'
#575000
b10 9
1"
15
0!
06
1'
#580000
0'
#585000
b1 9
b110 %
b110 +
b110 1
b1111100000000000 7
1!
16
1'
#590000
0'
#595000
b10 9
0!
06
1'
#600000
0'
#605000
b1 9
b101 %
b101 +
b101 1
b1111000000000000 7
1!
16
1'
#610000
0'
#615000
b10 9
0!
06
1'
#620000
0'
#625000
b1 9
b100 %
b100 +
b100 1
b1110000000000000 7
1!
16
1'
#630000
0'
#635000
b10 9
0!
06
1'
#640000
0'
#645000
b1 9
b11 %
b11 +
b11 1
b1100000000000000 7
1!
16
1'
#650000
0'
#655000
b10 9
0!
06
1'
#660000
0'
#665000
b1 9
b10 %
b10 +
b10 1
b1000000000000000 7
1!
16
1'
#670000
0'
#675000
b10 9
0!
06
1'
#680000
0'
#685000
b1 9
b1 %
b1 +
b1 1
b0 7
1!
16
1'
#690000
0'
#695000
b10 9
0"
05
0!
06
1'
#700000
0'
#705000
b0 9
1$
14
0&
02
1#
13
b0 %
b0 +
b0 1
0!
06
1'
#710000
0'
#715000
0$
04
1'
