Assignment/q5/sequence_detector.v
`timescale 1ns / 1ps

module sequence_detector (input data,rst,clk,  
                          output reg y  
);

// State encoding for 5 states
reg [2:0] state;
parameter S0 = 3'b000,
          S1 = 3'b001,
          S2 = 3'b010,
          S3 = 3'b011,
          S4 = 3'b100;

always @(posedge clk) begin
    if (rst) begin
        state <= S0;
        y <= 0;
    end
    else begin
        case (state)
            S0: begin
                if (data) begin
                    state <= S1;  // first bit '1' matched
                    y <= 0;
                end else begin
                    state <= S0;  // stay in idle
                    y <= 0;
                end
            end
            S1: begin
                if (data) begin
                    state <= S1;  // another '1' -> restart from first bit
                    y <= 0;
                end else begin
                    state <= S2;  // '0' gives "10"
                    y <= 0;
                end
            end
            S2: begin
                if (data) begin
                    state <= S3;  // '1' gives "101"
                    y <= 0;
                end else begin
                    state <= S0;  // '0' resets
                    y <= 0;
                end
            end
            S3: begin
                if (data) begin
                    state <= S4;  // '1' gives "1011"
                    y <= 0;
                end else begin
                    state <= S2;  // '0' gives "1010" -> suffix "10" matches
                    y <= 0;
                end
            end
            S4: begin
                if (data) begin
                    state <= S1;  // '1' after "1011" -> suffix "1" matches
                    y <= 0;
                end else begin
                    state <= S0;  // '0' completes "10110" -> detect!
                    y <= 1;
                end
            end
            default: begin
                state <= S0;
                y <= 0;
            end
        endcase
    end
end

endmodule

Assignment/q5/tb_sequence_detector.v
`timescale 1ns / 1ps
module tb_sequence_detector();
reg data, rst, clk;
wire y;

sequence_detector dut(.data(data),.rst(rst),.clk(clk),.y(y));

always #5 clk = ~clk;

initial begin
    $dumpfile("sequence_detector.vcd");
    $dumpvars(0, tb_sequence_detector);
    $monitor("Time=%0t, clk=%b, rst=%b, data=%b, y=%b", $time, clk, rst, data, y);

    rst = 1;data = 0;clk = 0;
    #20;
    rst = 0;
    #10;

    #10 data = 1; // bit 1
    #10 data = 0; // bit 2
    #10 data = 1; // bit 3
    #10 data = 1; // bit 4
    #10 data = 0; // bit 5 -> detection should occur here (y = 1)

    // Additional bits to observe behavior after detection
    #10 data = 1;
    #10 data = 0;
    #10 data = 1;
    #10 data = 1;
    #10 data = 0; // another detection
    #10 data = 1;
    #10 data = 0;
    #10 data = 1;
    #10 data = 0;
    #10 data = 1;
    #10 data = 1;
    #10 data = 0; // detection again
    #10;

    $finish;
end

endmodule

Assignment/q5/sequence_detector.vcd
$date
	Fri Mar  6 11:25:07 2026
$end
$version
	Icarus Verilog
$end
$timescale
	1ps
$end
$scope module tb_sequence_detector $end
$var wire 1 ! y $end
$var reg 1 " clk $end
$var reg 1 # data $end
$var reg 1 $ rst $end
$scope module dut $end
$var wire 1 " clk $end
$var wire 1 # data $end
$var wire 1 $ rst $end
$var parameter 3 % S0 $end
$var parameter 3 & S1 $end
$var parameter 3 ' S2 $end
$var parameter 3 ( S3 $end
$var parameter 3 ) S4 $end
$var reg 3 * state [2:0] $end
$var reg 1 ! y $end
$upscope $end
$upscope $end
$enddefinitions $end
$comment Show the parameter values. $end
$dumpall
b100 )
b11 (
b10 '
b1 &
b0 %
$end
#0
$dumpvars
bx *
1$
0#
0"
x!
$end
#5000
0!
b0 *
1"
#10000
0"
#15000
1"
#20000
0"
0$
#25000
1"
#30000
0"
#35000
1"
#40000
0"
1#
#45000
b1 *
1"
#50000
0"
0#
#55000
b10 *
1"
#60000
0"
1#
#65000
b11 *
1"
#70000
0"
#75000
b100 *
1"
#80000
0"
0#
#85000
1!
b0 *
1"
#90000
0"
1#
#95000
0!
b1 *
1"
#100000
0"
0#
#105000
b10 *
1"
#110000
0"
1#
#115000
b11 *
1"
#120000
0"
#125000
b100 *
1"
#130000
0"
0#
#135000
1!
b0 *
1"
#140000
0"
1#
#145000
0!
b1 *
1"
#150000
0"
0#
#155000
b10 *
1"
#160000
0"
1#
#165000
b11 *
1"
#170000
0"
0#
#175000
b10 *
1"
#180000
0"
1#
#185000
b11 *
1"
#190000
0"
#195000
b100 *
1"
#200000
0"
0#
#205000
1!
b0 *
1"
