Assignment/q3/decade_counter.v
module decade_counter (input clk,rst,
                       output reg [3:0] count
);

always @(posedge clk) begin
    if (rst)
        count <= 4'd0;
    else begin
        if (count >= 4'd9)
            count <= 4'd0;
        else
            count <= count + 4'd1;
    end
end

endmodule

Assignment/q3/tb_decade_counter.v
module tb_decade_counter();
reg clk,rst;
wire [3:0] count;

decade_counter uut(.clk(clk),.rst(rst),.count(count));

initial begin
    $dumpfile("counter.vcd");   // VCD file name
    $dumpvars(0, tb_decade_counter);
    $monitor("Time = %0t | Reset = %b | Counter = %d", $time, rst, count);
    clk = 0;rst = 1;

    #20; rst = 0;clk=1;
    #200;
    #20;rst = 1;
    #20;rst = 0;
    #200;

    $finish;
end

always #10 clk = ~clk;
endmodule

Assignment/q3/counter.vcd
$date
	Wed Mar  4 19:28:55 2026
$end
$version
	Icarus Verilog
$end
$timescale
	1s
$end
$scope module tb_decade_counter $end
$var wire 4 ! count [3:0] $end
$var reg 1 " clk $end
$var reg 1 # rst $end
$scope module uut $end
$var wire 1 " clk $end
$var wire 1 # rst $end
$var reg 4 $ count [3:0] $end
$upscope $end
$upscope $end
$enddefinitions $end
$comment Show the parameter values. $end
$dumpall
$end
#0
$dumpvars
bx $
1#
0"
bx !
$end
#10
b0 !
b0 $
1"
#20
0"
0#
#30
b1 !
b1 $
1"
#40
0"
#50
b10 !
b10 $
1"
#60
0"
#70
b11 !
b11 $
1"
#80
0"
#90
b100 !
b100 $
1"
#100
0"
#110
b101 !
b101 $
1"
#120
0"
#130
b110 !
b110 $
1"
#140
0"
#150
b111 !
b111 $
1"
#160
0"
#170
b1000 !
b1000 $
1"
#180
0"
#190
b1001 !
b1001 $
1"
#200
0"
#210
b0 !
b0 $
1"
#220
0"
#230
b1 !
b1 $
1"
#240
0"
1#
#250
b0 !
b0 $
1"
#260
0"
0#
#270
b1 !
b1 $
1"
#280
0"
#290
b10 !
b10 $
1"
#300
0"
#310
b11 !
b11 $
1"
#320
0"
#330
b100 !
b100 $
1"
#340
0"
#350
b101 !
b101 $
1"
#360
0"
#370
b110 !
b110 $
1"
#380
0"
#390
b111 !
b111 $
1"
#400
0"
#410
b1000 !
b1000 $
1"
#420
0"
#430
b1001 !
b1001 $
1"
#440
0"
#450
b0 !
b0 $
1"
